{
  "meta": {
    "ticker": "HPQ",
    "name": "HP Inc.",
    "market": "NYQ",
    "price": 19.73,
    "change": -0.03,
    "changePercent": -0.15
  },
  "score": {
    "total": 6,
    "stars": 0.5,
    "note": "/ 100 (Win Rate: 50%)"
  },
  "raw_metrics": {
    "targetMA_label": "Daily 50MA",
    "targetMA_price": 18.93,
    "maDistance_pct": 4.2,
    "bb2Confluence_pct": 4.6,
    "bb3Confluence_pct": 8.17,
    "maKnock_count": 3,
    "expectedRsi": 46.65
  },
  "metrics": {
    "maDistance": "+4.20%",
    "bbConfluence": "4.60%",
    "maKnock": "3 times recently",
    "expectedRsi": "46.65"
  },
  "resistances": {
    "horizontal": [
      {
        "price": 20.16,
        "touches": 2,
        "strength_score": 1.06
      },
      {
        "price": 21.42,
        "touches": 1,
        "strength_score": 0.944
      },
      {
        "price": 25.2,
        "touches": 2,
        "strength_score": 0.668
      },
      {
        "price": 24.36,
        "touches": 1,
        "strength_score": 0.301
      }
    ],
    "trendline_clusters": []
  },
  "summary": "The SwingRatings algorithm indicates that HPQ is currently testing its Daily 50MA support zone near $18.93. Based on historical price action, bounces from this level have yielded a win rate of 50.0%. The asset has recently tested this support 3 time(s), which may have partially consumed buy-side liquidity. In the event of a successful bounce, traders should monitor overhead supply, particularly a primary horizontal resistance at $20.16. This setup presents a structured risk-reward profile for swing positioning.",
  "chartData": {
    "candles": [
      {
        "time": "2025-09-23",
        "open": 27.578758744478215,
        "high": 28.064985087054737,
        "low": 27.578758744478215,
        "close": 27.744075775146484
      },
      {
        "time": "2025-09-24",
        "open": 27.695451991813815,
        "high": 27.948289912199964,
        "low": 26.71327455851596,
        "close": 26.742448806762695
      },
      {
        "time": "2025-09-25",
        "open": 26.32429430355905,
        "high": 26.392365695819333,
        "low": 25.993660237032262,
        "close": 26.110355377197266
      },
      {
        "time": "2025-09-26",
        "open": 26.02283448704283,
        "high": 26.158977271570024,
        "low": 25.594954779492085,
        "close": 25.974210739135742
      },
      {
        "time": "2025-09-29",
        "open": 26.14925193786621,
        "high": 26.304844218080618,
        "low": 25.94503776563716,
        "close": 26.14925193786621
      },
      {
        "time": "2025-09-30",
        "open": 26.158975802380397,
        "high": 26.499334599388835,
        "low": 26.110353912010428,
        "close": 26.47988510131836
      },
      {
        "time": "2025-10-01",
        "open": 26.44098866235261,
        "high": 26.470161055427024,
        "low": 25.672750161417593,
        "close": 25.964487075805664
      },
      {
        "time": "2025-10-02",
        "open": 26.022832909058614,
        "high": 26.402088845704778,
        "low": 25.692198862564855,
        "close": 25.750545501708984
      },
      {
        "time": "2025-10-03",
        "open": 25.876966979811073,
        "high": 26.53823511358368,
        "low": 25.77972133870222,
        "close": 25.906139373779297
      },
      {
        "time": "2025-10-06",
        "open": 26.052008256070106,
        "high": 26.168701539285696,
        "low": 25.7116494462131,
        "close": 25.87696647644043
      },
      {
        "time": "2025-10-07",
        "open": 26.042282384065317,
        "high": 26.100629023157968,
        "low": 25.478259926686455,
        "close": 25.81861686706543
      },
      {
        "time": "2025-10-08",
        "open": 25.847792128541332,
        "high": 26.431264106787772,
        "low": 25.711649347046137,
        "close": 26.285396575927734
      },
      {
        "time": "2025-10-09",
        "open": 26.411815407815553,
        "high": 26.58685719207043,
        "low": 25.99366044649698,
        "close": 26.227048873901367
      },
      {
        "time": "2025-10-10",
        "open": 26.353467438178605,
        "high": 26.43126357673091,
        "low": 24.758643815647016,
        "close": 24.84616470336914
      },
      {
        "time": "2025-10-13",
        "open": 25.312943296567113,
        "high": 26.62575289796721,
        "low": 25.293493798298872,
        "close": 26.596580505371094
      },
      {
        "time": "2025-10-14",
        "open": 26.732723046140197,
        "high": 27.948288855012375,
        "low": 26.645202159516902,
        "close": 27.753799438476562
      },
      {
        "time": "2025-10-15",
        "open": 28.064983965404966,
        "high": 28.191401993307647,
        "low": 27.6079300345737,
        "close": 27.821870803833008
      },
      {
        "time": "2025-10-16",
        "open": 27.899666396052197,
        "high": 27.93856353664424,
        "low": 26.343741821440545,
        "close": 26.450712203979492
      },
      {
        "time": "2025-10-17",
        "open": 26.35346707978424,
        "high": 26.849418151862825,
        "low": 26.256221444214795,
        "close": 26.616029739379883
      },
      {
        "time": "2025-10-20",
        "open": 26.800795133278474,
        "high": 27.316195717405353,
        "low": 26.742448492277443,
        "close": 26.898040771484375
      },
      {
        "time": "2025-10-21",
        "open": 26.96611285040763,
        "high": 27.71490187246638,
        "low": 26.90776620791663,
        "close": 27.384267807006836
      },
      {
        "time": "2025-10-22",
        "open": 26.450713432466017,
        "high": 27.199500580597018,
        "low": 26.227047908150563,
        "close": 26.898040771484375
      },
      {
        "time": "2025-10-23",
        "open": 27.014736414274275,
        "high": 27.3648181216437,
        "low": 26.907766024763617,
        "close": 27.063358306884766
      },
      {
        "time": "2025-10-24",
        "open": 27.481512745913502,
        "high": 27.646829774421647,
        "low": 26.878591272881938,
        "close": 26.898040771484375
      },
      {
        "time": "2025-10-27",
        "open": 27.170328405008135,
        "high": 27.32592068546064,
        "low": 26.946662878902156,
        "close": 27.15087890625
      },
      {
        "time": "2025-10-28",
        "open": 27.03418264241391,
        "high": 27.41344043317462,
        "low": 26.752172341393084,
        "close": 27.29674530029297
      },
      {
        "time": "2025-10-29",
        "open": 27.111979159066312,
        "high": 27.471787456917678,
        "low": 26.810519355875968,
        "close": 26.936939239501953
      },
      {
        "time": "2025-10-30",
        "open": 26.635479235678346,
        "high": 27.063358949067762,
        "low": 26.431265056100933,
        "close": 26.752174377441406
      },
      {
        "time": "2025-10-31",
        "open": 26.761896910795812,
        "high": 27.111978597479315,
        "low": 26.538233250313482,
        "close": 26.907764434814453
      },
      {
        "time": "2025-11-03",
        "open": 26.839694576583046,
        "high": 27.03418400142116,
        "low": 25.96448752779577,
        "close": 26.265947341918945
      },
      {
        "time": "2025-11-04",
        "open": 25.789444360391624,
        "high": 25.98393377477214,
        "low": 25.196247658697708,
        "close": 25.225421905517578
      },
      {
        "time": "2025-11-05",
        "open": 25.225423595629984,
        "high": 25.974210766113597,
        "low": 25.05038181259531,
        "close": 25.906139373779297
      },
      {
        "time": "2025-11-06",
        "open": 25.935313491220075,
        "high": 25.95476299030462,
        "low": 25.381015750954745,
        "close": 25.449087142944336
      },
      {
        "time": "2025-11-07",
        "open": 25.293494308816346,
        "high": 25.60467886816409,
        "low": 25.108727781151266,
        "close": 25.55605697631836
      },
      {
        "time": "2025-11-10",
        "open": 25.83806668427457,
        "high": 25.847791433377868,
        "low": 24.4863580906221,
        "close": 24.59332847595215
      },
      {
        "time": "2025-11-11",
        "open": 24.51553251251248,
        "high": 24.573881011962335,
        "low": 23.95151000147525,
        "close": 24.048755645751953
      },
      {
        "time": "2025-11-12",
        "open": 24.165449831138456,
        "high": 24.622501929858213,
        "low": 24.165449831138456,
        "close": 24.515531539916992
      },
      {
        "time": "2025-11-13",
        "open": 24.505808992755533,
        "high": 24.739197420186706,
        "low": 24.25297106600351,
        "close": 24.291868209838867
      },
      {
        "time": "2025-11-14",
        "open": 24.01958224491787,
        "high": 24.311317310724036,
        "low": 23.795916716006413,
        "close": 23.854265213012695
      },
      {
        "time": "2025-11-17",
        "open": 22.910985076127698,
        "high": 23.32914003359508,
        "low": 22.15247315775089,
        "close": 22.239994049072266
      },
      {
        "time": "2025-11-18",
        "open": 22.084400177001953,
        "high": 22.376137103192356,
        "low": 21.78294035593092,
        "close": 22.084400177001953
      },
      {
        "time": "2025-11-19",
        "open": 22.035777806688138,
        "high": 22.162197695077793,
        "low": 21.821838882621588,
        "close": 21.851011276245117
      },
      {
        "time": "2025-11-20",
        "open": 22.055227305837224,
        "high": 22.30806522781247,
        "low": 21.65652185132411,
        "close": 21.98715591430664
      },
      {
        "time": "2025-11-21",
        "open": 22.171919964592572,
        "high": 23.591701816438846,
        "low": 22.142747571791585,
        "close": 23.299964904785156
      },
      {
        "time": "2025-11-24",
        "open": 23.38748570107637,
        "high": 23.825090139437517,
        "low": 23.309689562568416,
        "close": 23.70839500427246
      },
      {
        "time": "2025-11-25",
        "open": 23.727843437261132,
        "high": 24.359937266109103,
        "low": 23.533354027126617,
        "close": 23.650047302246094
      },
      {
        "time": "2025-11-26",
        "open": 23.436109273093578,
        "high": 23.90288610067965,
        "low": 22.852637311207875,
        "close": 23.319414138793945
      },
      {
        "time": "2025-11-28",
        "open": 23.48473081511827,
        "high": 23.757018221237832,
        "low": 23.183271016961537,
        "close": 23.74729347229004
      },
      {
        "time": "2025-12-01",
        "open": 23.33886461843955,
        "high": 24.039029889262462,
        "low": 23.319415119437334,
        "close": 23.718120574951172
      },
      {
        "time": "2025-12-02",
        "open": 24.068203147876098,
        "high": 24.748920746506197,
        "low": 23.757018595864473,
        "close": 24.457183837890625
      },
      {
        "time": "2025-12-03",
        "open": 24.544704195558893,
        "high": 24.76836785564198,
        "low": 24.282141539910292,
        "close": 24.496082305908203
      },
      {
        "time": "2025-12-04",
        "open": 24.505807690695605,
        "high": 25.21569768493117,
        "low": 24.418286803208343,
        "close": 25.1865234375
      },
      {
        "time": "2025-12-05",
        "open": 25.215696598279365,
        "high": 25.32266697944426,
        "low": 24.93368444968324,
        "close": 25.196247100830078
      },
      {
        "time": "2025-12-08",
        "open": 25.030932190177445,
        "high": 25.06010643880837,
        "low": 24.223796526118495,
        "close": 24.3793888092041
      },
      {
        "time": "2025-12-09",
        "open": 24.10710368024416,
        "high": 24.816993716601488,
        "low": 24.06820468136117,
        "close": 24.680849075317383
      },
      {
        "time": "2025-12-10",
        "open": 24.641951375780945,
        "high": 24.875339799398944,
        "low": 24.43773534586125,
        "close": 24.787818908691406
      },
      {
        "time": "2025-12-11",
        "open": 24.738615243763242,
        "high": 25.08302753423908,
        "low": 24.709095423682676,
        "close": 25.004304885864258
      },
      {
        "time": "2025-12-12",
        "open": 24.9846249102971,
        "high": 25.06334756231351,
        "low": 24.276121042149406,
        "close": 24.345003128051758
      },
      {
        "time": "2025-12-15",
        "open": 24.55164993365537,
        "high": 24.630372581410462,
        "low": 23.99074895689236,
        "close": 24.0989933013916
      },
      {
        "time": "2025-12-16",
        "open": 24.069471719111743,
        "high": 24.531968919156334,
        "low": 24.030111333495004,
        "close": 24.433565139770508
      },
      {
        "time": "2025-12-17",
        "open": 24.374524974133198,
        "high": 24.492608014425503,
        "low": 23.83330509595586,
        "close": 24.039953231811523
      },
      {
        "time": "2025-12-18",
        "open": 23.488894054494686,
        "high": 23.725062005843554,
        "low": 22.61310245673459,
        "close": 23.075599670410156
      },
      {
        "time": "2025-12-19",
        "open": 23.016555419066698,
        "high": 23.154321459902953,
        "low": 22.701664828976917,
        "close": 22.88863182067871
      },
      {
        "time": "2025-12-22",
        "open": 23.114960415641608,
        "high": 23.272405718982434,
        "low": 22.721347157289546,
        "close": 22.80006980895996
      },
      {
        "time": "2025-12-23",
        "open": 22.780388724568514,
        "high": 23.016556680074785,
        "low": 22.416297163665707,
        "close": 22.563901901245117
      },
      {
        "time": "2025-12-24",
        "open": 22.622942030533444,
        "high": 22.898472233471885,
        "low": 22.603260899560137,
        "close": 22.79022789001465
      },
      {
        "time": "2025-12-26",
        "open": 22.809909173156264,
        "high": 22.93783277154425,
        "low": 22.76070634539476,
        "close": 22.88863182067871
      },
      {
        "time": "2025-12-29",
        "open": 22.809910123744807,
        "high": 22.90831390647277,
        "low": 22.29821195507623,
        "close": 22.367094039916992
      },
      {
        "time": "2025-12-30",
        "open": 22.31789313812584,
        "high": 22.613102610089943,
        "low": 22.298212006155953,
        "close": 22.534379959106445
      },
      {
        "time": "2025-12-31",
        "open": 22.495019862858356,
        "high": 22.534380250410894,
        "low": 21.914439600513823,
        "close": 21.924280166625977
      },
      {
        "time": "2026-01-02",
        "open": 22.180128639802692,
        "high": 22.23917015794233,
        "low": 21.658589911697185,
        "close": 21.766834259033203
      },
      {
        "time": "2026-01-05",
        "open": 21.756994562782776,
        "high": 21.943959690513626,
        "low": 21.264977512530038,
        "close": 21.314178466796875
      },
      {
        "time": "2026-01-06",
        "open": 21.2748174374892,
        "high": 22.012842990622467,
        "low": 21.018968353842144,
        "close": 21.796354293823242
      },
      {
        "time": "2026-01-07",
        "open": 21.78651375732401,
        "high": 21.80619488922254,
        "low": 20.59583343090366,
        "close": 20.753278732299805
      },
      {
        "time": "2026-01-08",
        "open": 20.576152703470225,
        "high": 21.550346228844592,
        "low": 20.320303614448257,
        "close": 21.04848861694336
      },
      {
        "time": "2026-01-09",
        "open": 21.264976661914794,
        "high": 21.294496482535642,
        "low": 20.585992634194987,
        "close": 21.12721061706543
      },
      {
        "time": "2026-01-12",
        "open": 21.137052132210215,
        "high": 21.274818183246918,
        "low": 20.792639819962613,
        "close": 20.841842651367188
      },
      {
        "time": "2026-01-13",
        "open": 20.66471606790125,
        "high": 21.07801046433512,
        "low": 20.418707543283375,
        "close": 20.743438720703125
      },
      {
        "time": "2026-01-14",
        "open": 20.6745567845874,
        "high": 21.245296490778983,
        "low": 20.36950673737192,
        "close": 20.43838882446289
      },
      {
        "time": "2026-01-15",
        "open": 20.536792001982576,
        "high": 20.684396738075446,
        "low": 20.182539133842855,
        "close": 20.280942916870117
      },
      {
        "time": "2026-01-16",
        "open": 19.759404225419292,
        "high": 20.40886656721615,
        "low": 19.661000442169087,
        "close": 20.044775009155273
      },
      {
        "time": "2026-01-20",
        "open": 19.69052149303257,
        "high": 19.95621113600672,
        "low": 19.267386552791372,
        "close": 19.48387336730957
      },
      {
        "time": "2026-01-21",
        "open": 19.552757147649736,
        "high": 19.670840181068005,
        "low": 18.972176915471326,
        "close": 19.218185424804688
      },
      {
        "time": "2026-01-22",
        "open": 19.355950010203863,
        "high": 19.877488737010875,
        "low": 19.336268878574312,
        "close": 19.513395309448242
      },
      {
        "time": "2026-01-23",
        "open": 19.38547113256972,
        "high": 19.39530982119661,
        "low": 18.893454117802936,
        "close": 19.119781494140625
      },
      {
        "time": "2026-01-26",
        "open": 19.168982660197457,
        "high": 19.287067570902238,
        "low": 18.991856232588276,
        "close": 19.149301528930664
      },
      {
        "time": "2026-01-27",
        "open": 19.18866503227476,
        "high": 19.20834616481421,
        "low": 18.84425272041881,
        "close": 19.060741424560547
      },
      {
        "time": "2026-01-28",
        "open": 19.109941122481615,
        "high": 19.346109066738,
        "low": 18.706487316431627,
        "close": 18.745847702026367
      },
      {
        "time": "2026-01-29",
        "open": 18.76552894616898,
        "high": 19.316587486082494,
        "low": 18.637605346096485,
        "close": 19.080419540405273
      },
      {
        "time": "2026-01-30",
        "open": 18.991857362915024,
        "high": 19.13946397930501,
        "low": 18.657285619050956,
        "close": 19.129623413085938
      },
      {
        "time": "2026-02-02",
        "open": 19.168982227911204,
        "high": 19.61179828694806,
        "low": 19.090259581515312,
        "close": 19.49371337890625
      },
      {
        "time": "2026-02-03",
        "open": 18.75568916370378,
        "high": 18.84425238164304,
        "low": 18.027504164900165,
        "close": 18.69664764404297
      },
      {
        "time": "2026-02-04",
        "open": 19.03121938669641,
        "high": 20.2218997306787,
        "low": 19.001697688413184,
        "close": 19.503555297851562
      },
      {
        "time": "2026-02-05",
        "open": 19.483873388133436,
        "high": 19.621639431061343,
        "low": 18.48016008620724,
        "close": 18.84425163269043
      },
      {
        "time": "2026-02-06",
        "open": 18.834411770505266,
        "high": 19.582277899705893,
        "low": 18.834411770505266,
        "close": 19.33626937866211
      },
      {
        "time": "2026-02-09",
        "open": 19.08041923204922,
        "high": 19.306748485282874,
        "low": 18.83441072466583,
        "close": 19.119781494140625
      },
      {
        "time": "2026-02-10",
        "open": 19.287067135953013,
        "high": 20.093974730734892,
        "low": 19.287067135953013,
        "close": 19.49371337890625
      },
      {
        "time": "2026-02-11",
        "open": 19.5232359709308,
        "high": 19.592118055075748,
        "low": 19.188664239173022,
        "close": 19.44451332092285
      },
      {
        "time": "2026-02-12",
        "open": 18.696647281522928,
        "high": 18.952496364287082,
        "low": 17.968462296838506,
        "close": 18.568723678588867
      },
      {
        "time": "2026-02-13",
        "open": 18.80489084636055,
        "high": 19.424831457199534,
        "low": 18.755688018899708,
        "close": 18.952495574951172
      },
      {
        "time": "2026-02-17",
        "open": 18.863933360166698,
        "high": 19.060740926627687,
        "low": 18.19478988647461,
        "close": 18.19478988647461
      },
      {
        "time": "2026-02-18",
        "open": 18.106226863117836,
        "high": 18.421117471310065,
        "low": 17.958622125139737,
        "close": 18.057025909423828
      },
      {
        "time": "2026-02-19",
        "open": 18.00782172895707,
        "high": 18.322714190440852,
        "low": 17.968461344331555,
        "close": 18.047183990478516
      },
      {
        "time": "2026-02-20",
        "open": 18.155429645643306,
        "high": 18.617924990589227,
        "low": 17.830698472192754,
        "close": 18.293193817138672
      },
      {
        "time": "2026-02-23",
        "open": 18.17510894904788,
        "high": 18.362075951498042,
        "low": 17.840537208619615,
        "close": 18.057025909423828
      },
      {
        "time": "2026-02-24",
        "open": 18.096385126892713,
        "high": 18.509679492645535,
        "low": 17.712612457585074,
        "close": 17.909420013427734
      },
      {
        "time": "2026-02-25",
        "open": 17.417404286675037,
        "high": 18.893455433786613,
        "low": 17.27963823665528,
        "close": 17.919260025024414
      },
      {
        "time": "2026-02-26",
        "open": 18.30303354651522,
        "high": 18.87377321548556,
        "low": 18.263671283946792,
        "close": 18.509679794311523
      },
      {
        "time": "2026-02-27",
        "open": 18.30303305974191,
        "high": 18.736008551999632,
        "low": 18.116066071306268,
        "close": 18.686805725097656
      },
      {
        "time": "2026-03-02",
        "open": 18.4211170142511,
        "high": 18.6671255304094,
        "low": 18.243992459209785,
        "close": 18.401437759399414
      },
      {
        "time": "2026-03-03",
        "open": 18.184948929556324,
        "high": 18.75568860774924,
        "low": 18.165267797954083,
        "close": 18.70648765563965
      },
      {
        "time": "2026-03-04",
        "open": 18.70648770952024,
        "high": 19.01153774264957,
        "low": 18.37191597890251,
        "close": 18.8737735748291
      },
      {
        "time": "2026-03-05",
        "open": 18.94265626402281,
        "high": 19.267387439187356,
        "low": 18.804892091800298,
        "close": 19.031219482421875
      },
      {
        "time": "2026-03-06",
        "open": 18.844251501879285,
        "high": 19.178823225830854,
        "low": 18.588402426098913,
        "close": 19.149301528930664
      },
      {
        "time": "2026-03-09",
        "open": 18.863933612289593,
        "high": 18.883614744577947,
        "low": 18.20463069579835,
        "close": 18.627765655517578
      },
      {
        "time": "2026-03-10",
        "open": 18.60808471965122,
        "high": 18.88361494390837,
        "low": 18.17510918921744,
        "close": 18.490001678466797
      },
      {
        "time": "2026-03-11",
        "open": 18.700000762939453,
        "high": 19.040000915527344,
        "low": 18.260000228881836,
        "close": 18.459999084472656
      },
      {
        "time": "2026-03-12",
        "open": 18.549999237060547,
        "high": 19.18000030517578,
        "low": 18.450000762939453,
        "close": 18.950000762939453
      },
      {
        "time": "2026-03-13",
        "open": 19.100000381469727,
        "high": 19.15999984741211,
        "low": 18.6200008392334,
        "close": 18.93000030517578
      },
      {
        "time": "2026-03-16",
        "open": 19.0,
        "high": 19.1299991607666,
        "low": 18.399999618530273,
        "close": 18.68000030517578
      },
      {
        "time": "2026-03-17",
        "open": 18.799999237060547,
        "high": 19.010000228881836,
        "low": 18.700000762939453,
        "close": 18.75
      },
      {
        "time": "2026-03-18",
        "open": 18.600000381469727,
        "high": 18.8799991607666,
        "low": 18.209999084472656,
        "close": 18.219999313354492
      },
      {
        "time": "2026-03-19",
        "open": 18.149999618530273,
        "high": 18.889999389648438,
        "low": 18.010000228881836,
        "close": 18.479999542236328
      },
      {
        "time": "2026-03-20",
        "open": 18.43000030517578,
        "high": 18.540000915527344,
        "low": 18.09000015258789,
        "close": 18.270000457763672
      },
      {
        "time": "2026-03-23",
        "open": 18.3700008392334,
        "high": 18.670000076293945,
        "low": 18.020000457763672,
        "close": 18.530000686645508
      },
      {
        "time": "2026-03-24",
        "open": 18.350000381469727,
        "high": 19.010000228881836,
        "low": 18.18000030517578,
        "close": 18.889999389648438
      },
      {
        "time": "2026-03-25",
        "open": 19.1200008392334,
        "high": 20.139999389648438,
        "low": 19.09000015258789,
        "close": 19.459999084472656
      },
      {
        "time": "2026-03-26",
        "open": 19.34000015258789,
        "high": 20.139999389648438,
        "low": 19.270000457763672,
        "close": 19.31999969482422
      },
      {
        "time": "2026-03-27",
        "open": 19.290000915527344,
        "high": 19.530000686645508,
        "low": 18.920000076293945,
        "close": 19.440000534057617
      },
      {
        "time": "2026-03-30",
        "open": 19.579999923706055,
        "high": 19.690000534057617,
        "low": 18.829999923706055,
        "close": 19.049999237060547
      },
      {
        "time": "2026-03-31",
        "open": 19.110000610351562,
        "high": 19.329999923706055,
        "low": 18.670000076293945,
        "close": 19.209999084472656
      },
      {
        "time": "2026-04-01",
        "open": 19.200000762939453,
        "high": 19.309999465942383,
        "low": 18.639999389648438,
        "close": 18.950000762939453
      },
      {
        "time": "2026-04-02",
        "open": 19.0,
        "high": 19.520000457763672,
        "low": 18.639999389648438,
        "close": 19.510000228881836
      },
      {
        "time": "2026-04-06",
        "open": 19.510000228881836,
        "high": 19.520000457763672,
        "low": 18.93000030517578,
        "close": 18.940000534057617
      },
      {
        "time": "2026-04-07",
        "open": 18.770000457763672,
        "high": 18.989999771118164,
        "low": 18.530000686645508,
        "close": 18.610000610351562
      },
      {
        "time": "2026-04-08",
        "open": 19.030000686645508,
        "high": 19.149999618530273,
        "low": 18.520000457763672,
        "close": 18.889999389648438
      },
      {
        "time": "2026-04-09",
        "open": 18.829999923706055,
        "high": 18.969999313354492,
        "low": 18.1299991607666,
        "close": 18.3799991607666
      },
      {
        "time": "2026-04-10",
        "open": 18.75,
        "high": 18.93000030517578,
        "low": 18.1299991607666,
        "close": 18.260000228881836
      },
      {
        "time": "2026-04-13",
        "open": 18.290000915527344,
        "high": 19.420000076293945,
        "low": 18.149999618530273,
        "close": 19.229999542236328
      },
      {
        "time": "2026-04-14",
        "open": 18.770000457763672,
        "high": 19.110000610351562,
        "low": 18.520000457763672,
        "close": 18.989999771118164
      },
      {
        "time": "2026-04-15",
        "open": 19.18000030517578,
        "high": 19.34000015258789,
        "low": 18.850000381469727,
        "close": 19.229999542236328
      },
      {
        "time": "2026-04-16",
        "open": 19.420000076293945,
        "high": 19.850000381469727,
        "low": 19.270000457763672,
        "close": 19.719999313354492
      },
      {
        "time": "2026-04-17",
        "open": 19.799999237060547,
        "high": 20.040000915527344,
        "low": 19.65999984741211,
        "close": 19.8799991607666
      },
      {
        "time": "2026-04-20",
        "open": 19.790000915527344,
        "high": 20.0,
        "low": 19.59000015258789,
        "close": 19.59000015258789
      },
      {
        "time": "2026-04-21",
        "open": 19.68000030517578,
        "high": 21.420000076293945,
        "low": 19.6299991607666,
        "close": 21.09000015258789
      },
      {
        "time": "2026-04-22",
        "open": 21.030000686645508,
        "high": 21.3799991607666,
        "low": 20.389999389648438,
        "close": 20.440000534057617
      },
      {
        "time": "2026-04-23",
        "open": 20.280000686645508,
        "high": 20.31999969482422,
        "low": 19.860000610351562,
        "close": 20.139999389648438
      },
      {
        "time": "2026-04-24",
        "open": 20.34000015258789,
        "high": 20.6200008392334,
        "low": 19.649999618530273,
        "close": 19.790000915527344
      },
      {
        "time": "2026-04-27",
        "open": 19.799999237060547,
        "high": 20.110000610351562,
        "low": 19.5,
        "close": 19.760000228881836
      },
      {
        "time": "2026-04-28",
        "open": 19.790000915527344,
        "high": 20.09000015258789,
        "low": 19.649999618530273,
        "close": 19.729999542236328
      }
    ],
    "ma_target": [
      {
        "time": "2025-09-23",
        "value": 25.862967987060546
      },
      {
        "time": "2025-09-24",
        "value": 25.925672073364257
      },
      {
        "time": "2025-09-25",
        "value": 25.97496406555176
      },
      {
        "time": "2025-09-26",
        "value": 26.017874603271483
      },
      {
        "time": "2025-09-29",
        "value": 26.058316802978517
      },
      {
        "time": "2025-09-30",
        "value": 26.10980041503906
      },
      {
        "time": "2025-10-01",
        "value": 26.139807891845702
      },
      {
        "time": "2025-10-02",
        "value": 26.156486434936525
      },
      {
        "time": "2025-10-03",
        "value": 26.179935417175294
      },
      {
        "time": "2025-10-06",
        "value": 26.20299346923828
      },
      {
        "time": "2025-10-07",
        "value": 26.221611099243162
      },
      {
        "time": "2025-10-08",
        "value": 26.253030319213867
      },
      {
        "time": "2025-10-09",
        "value": 26.2942582321167
      },
      {
        "time": "2025-10-10",
        "value": 26.313645095825194
      },
      {
        "time": "2025-10-13",
        "value": 26.37477966308594
      },
      {
        "time": "2025-10-14",
        "value": 26.449045791625977
      },
      {
        "time": "2025-10-15",
        "value": 26.523132934570313
      },
      {
        "time": "2025-10-16",
        "value": 26.57056709289551
      },
      {
        "time": "2025-10-17",
        "value": 26.614760704040528
      },
      {
        "time": "2025-10-20",
        "value": 26.64996036529541
      },
      {
        "time": "2025-10-21",
        "value": 26.706437911987305
      },
      {
        "time": "2025-10-22",
        "value": 26.732202415466308
      },
      {
        "time": "2025-10-23",
        "value": 26.7508752822876
      },
      {
        "time": "2025-10-24",
        "value": 26.770285453796387
      },
      {
        "time": "2025-10-27",
        "value": 26.798410911560058
      },
      {
        "time": "2025-10-28",
        "value": 26.827720718383787
      },
      {
        "time": "2025-10-29",
        "value": 26.846561012268065
      },
      {
        "time": "2025-10-30",
        "value": 26.871911430358885
      },
      {
        "time": "2025-10-31",
        "value": 26.89825553894043
      },
      {
        "time": "2025-11-03",
        "value": 26.889426879882812
      },
      {
        "time": "2025-11-04",
        "value": 26.864409027099608
      },
      {
        "time": "2025-11-05",
        "value": 26.862440719604493
      },
      {
        "time": "2025-11-06",
        "value": 26.849405822753905
      },
      {
        "time": "2025-11-07",
        "value": 26.81463352203369
      },
      {
        "time": "2025-11-10",
        "value": 26.75694808959961
      },
      {
        "time": "2025-11-11",
        "value": 26.680668983459473
      },
      {
        "time": "2025-11-12",
        "value": 26.618346710205078
      },
      {
        "time": "2025-11-13",
        "value": 26.547314987182617
      },
      {
        "time": "2025-11-14",
        "value": 26.459443893432617
      },
      {
        "time": "2025-11-17",
        "value": 26.33909481048584
      },
      {
        "time": "2025-11-18",
        "value": 26.221603050231934
      },
      {
        "time": "2025-11-19",
        "value": 26.10685359954834
      },
      {
        "time": "2025-11-20",
        "value": 25.995410537719728
      },
      {
        "time": "2025-11-21",
        "value": 25.917419815063475
      },
      {
        "time": "2025-11-24",
        "value": 25.85187644958496
      },
      {
        "time": "2025-11-25",
        "value": 25.785749626159667
      },
      {
        "time": "2025-11-26",
        "value": 25.709509315490724
      },
      {
        "time": "2025-11-28",
        "value": 25.635213928222655
      },
      {
        "time": "2025-12-01",
        "value": 25.56189098358154
      },
      {
        "time": "2025-12-02",
        "value": 25.50140438079834
      },
      {
        "time": "2025-12-03",
        "value": 25.436444511413573
      },
      {
        "time": "2025-12-04",
        "value": 25.40532600402832
      },
      {
        "time": "2025-12-05",
        "value": 25.387043838500976
      },
      {
        "time": "2025-12-08",
        "value": 25.355147399902343
      },
      {
        "time": "2025-12-09",
        "value": 25.325779342651366
      },
      {
        "time": "2025-12-10",
        "value": 25.291938018798827
      },
      {
        "time": "2025-12-11",
        "value": 25.272734375
      },
      {
        "time": "2025-12-12",
        "value": 25.244623527526855
      },
      {
        "time": "2025-12-15",
        "value": 25.208480606079103
      },
      {
        "time": "2025-12-16",
        "value": 25.179612579345704
      },
      {
        "time": "2025-12-17",
        "value": 25.144039306640625
      },
      {
        "time": "2025-12-18",
        "value": 25.079843368530273
      },
      {
        "time": "2025-12-19",
        "value": 25.01307502746582
      },
      {
        "time": "2025-12-22",
        "value": 24.972153129577638
      },
      {
        "time": "2025-12-23",
        "value": 24.891499557495116
      },
      {
        "time": "2025-12-24",
        "value": 24.792228126525877
      },
      {
        "time": "2025-12-26",
        "value": 24.693563346862792
      },
      {
        "time": "2025-12-29",
        "value": 24.611890983581542
      },
      {
        "time": "2025-12-30",
        "value": 24.530257987976075
      },
      {
        "time": "2025-12-31",
        "value": 24.430782775878907
      },
      {
        "time": "2026-01-02",
        "value": 24.318434104919433
      },
      {
        "time": "2026-01-05",
        "value": 24.206756858825685
      },
      {
        "time": "2026-01-06",
        "value": 24.101416778564452
      },
      {
        "time": "2026-01-07",
        "value": 23.97852153778076
      },
      {
        "time": "2026-01-08",
        "value": 23.85647373199463
      },
      {
        "time": "2026-01-09",
        "value": 23.73308303833008
      },
      {
        "time": "2026-01-12",
        "value": 23.611181106567383
      },
      {
        "time": "2026-01-13",
        "value": 23.491006393432617
      },
      {
        "time": "2026-01-14",
        "value": 23.361618881225585
      },
      {
        "time": "2026-01-15",
        "value": 23.241918792724608
      },
      {
        "time": "2026-01-16",
        "value": 23.138305854797363
      },
      {
        "time": "2026-01-20",
        "value": 23.00986053466797
      },
      {
        "time": "2026-01-21",
        "value": 22.885242500305175
      },
      {
        "time": "2026-01-22",
        "value": 22.764389266967772
      },
      {
        "time": "2026-01-23",
        "value": 22.654918327331544
      },
      {
        "time": "2026-01-26",
        "value": 22.556929244995118
      },
      {
        "time": "2026-01-27",
        "value": 22.447833442687987
      },
      {
        "time": "2026-01-28",
        "value": 22.33691303253174
      },
      {
        "time": "2026-01-29",
        "value": 22.24143611907959
      },
      {
        "time": "2026-01-30",
        "value": 22.179228706359865
      },
      {
        "time": "2026-02-02",
        "value": 22.12741497039795
      },
      {
        "time": "2026-02-03",
        "value": 22.064327697753907
      },
      {
        "time": "2026-02-04",
        "value": 22.014655685424806
      },
      {
        "time": "2026-02-05",
        "value": 21.92554141998291
      },
      {
        "time": "2026-02-06",
        "value": 21.8380989074707
      },
      {
        "time": "2026-02-09",
        "value": 21.747493591308594
      },
      {
        "time": "2026-02-10",
        "value": 21.670979576110838
      },
      {
        "time": "2026-02-11",
        "value": 21.584923973083495
      },
      {
        "time": "2026-02-12",
        "value": 21.48193603515625
      },
      {
        "time": "2026-02-13",
        "value": 21.37184226989746
      },
      {
        "time": "2026-02-17",
        "value": 21.24581642150879
      },
      {
        "time": "2026-02-18",
        "value": 21.103226470947266
      },
      {
        "time": "2026-02-19",
        "value": 20.960245208740233
      },
      {
        "time": "2026-02-20",
        "value": 20.838521308898926
      },
      {
        "time": "2026-02-23",
        "value": 20.706044845581054
      },
      {
        "time": "2026-02-24",
        "value": 20.56847686767578
      },
      {
        "time": "2026-02-25",
        "value": 20.426775970458984
      },
      {
        "time": "2026-02-26",
        "value": 20.31006950378418
      },
      {
        "time": "2026-02-27",
        "value": 20.2018257522583
      },
      {
        "time": "2026-03-02",
        "value": 20.08118320465088
      },
      {
        "time": "2026-03-03",
        "value": 19.97451389312744
      },
      {
        "time": "2026-03-04",
        "value": 19.89047737121582
      },
      {
        "time": "2026-03-05",
        "value": 19.813329124450682
      },
      {
        "time": "2026-03-06",
        "value": 19.740313758850096
      },
      {
        "time": "2026-03-09",
        "value": 19.661591033935547
      },
      {
        "time": "2026-03-10",
        "value": 19.57558650970459
      },
      {
        "time": "2026-03-11",
        "value": 19.487013854980468
      },
      {
        "time": "2026-03-12",
        "value": 19.418671989440917
      },
      {
        "time": "2026-03-13",
        "value": 19.346584396362303
      },
      {
        "time": "2026-03-16",
        "value": 19.281698799133302
      },
      {
        "time": "2026-03-17",
        "value": 19.221362113952637
      },
      {
        "time": "2026-03-18",
        "value": 19.15947853088379
      },
      {
        "time": "2026-03-19",
        "value": 19.09315143585205
      },
      {
        "time": "2026-03-20",
        "value": 19.043485870361327
      },
      {
        "time": "2026-03-23",
        "value": 18.99311611175537
      },
      {
        "time": "2026-03-24",
        "value": 18.94837188720703
      },
      {
        "time": "2026-03-25",
        "value": 18.92073501586914
      },
      {
        "time": "2026-03-26",
        "value": 18.892266235351563
      },
      {
        "time": "2026-03-27",
        "value": 18.872298469543455
      },
      {
        "time": "2026-03-30",
        "value": 18.847679595947266
      },
      {
        "time": "2026-03-31",
        "value": 18.830984077453614
      },
      {
        "time": "2026-04-01",
        "value": 18.82030662536621
      },
      {
        "time": "2026-04-02",
        "value": 18.826142921447754
      },
      {
        "time": "2026-04-06",
        "value": 18.81467502593994
      },
      {
        "time": "2026-04-07",
        "value": 18.80447940826416
      },
      {
        "time": "2026-04-08",
        "value": 18.799293365478515
      },
      {
        "time": "2026-04-09",
        "value": 18.785678520202637
      },
      {
        "time": "2026-04-10",
        "value": 18.775961570739746
      },
      {
        "time": "2026-04-13",
        "value": 18.77895317077637
      },
      {
        "time": "2026-04-14",
        "value": 18.776160697937012
      },
      {
        "time": "2026-04-15",
        "value": 18.770886421203613
      },
      {
        "time": "2026-04-16",
        "value": 18.791353454589842
      },
      {
        "time": "2026-04-17",
        "value": 18.798882331848144
      },
      {
        "time": "2026-04-20",
        "value": 18.813797302246094
      },
      {
        "time": "2026-04-21",
        "value": 18.84887191772461
      },
      {
        "time": "2026-04-22",
        "value": 18.875276298522948
      },
      {
        "time": "2026-04-23",
        "value": 18.888202018737793
      },
      {
        "time": "2026-04-24",
        "value": 18.89511177062988
      },
      {
        "time": "2026-04-27",
        "value": 18.918937301635744
      },
      {
        "time": "2026-04-28",
        "value": 18.934487380981444
      }
    ],
    "bbLower": [
      {
        "time": "2025-09-23",
        "value": 26.26384108352634
      },
      {
        "time": "2025-09-24",
        "value": 26.44573928957135
      },
      {
        "time": "2025-09-25",
        "value": 26.44877187551919
      },
      {
        "time": "2025-09-26",
        "value": 26.194363817097926
      },
      {
        "time": "2025-09-29",
        "value": 26.0139210529194
      },
      {
        "time": "2025-09-30",
        "value": 25.92206404161668
      },
      {
        "time": "2025-10-01",
        "value": 25.740329488514543
      },
      {
        "time": "2025-10-02",
        "value": 25.546632474310265
      },
      {
        "time": "2025-10-03",
        "value": 25.454294515833382
      },
      {
        "time": "2025-10-06",
        "value": 25.39661828070155
      },
      {
        "time": "2025-10-07",
        "value": 25.32677375102726
      },
      {
        "time": "2025-10-08",
        "value": 25.31065163396073
      },
      {
        "time": "2025-10-09",
        "value": 25.30069472593777
      },
      {
        "time": "2025-10-10",
        "value": 25.01091283541129
      },
      {
        "time": "2025-10-13",
        "value": 25.009619302300447
      },
      {
        "time": "2025-10-14",
        "value": 24.953675852803368
      },
      {
        "time": "2025-10-15",
        "value": 24.902615451001612
      },
      {
        "time": "2025-10-16",
        "value": 24.91105736840339
      },
      {
        "time": "2025-10-17",
        "value": 24.928011474805515
      },
      {
        "time": "2025-10-20",
        "value": 24.96028069736123
      },
      {
        "time": "2025-10-21",
        "value": 25.002113903181
      },
      {
        "time": "2025-10-22",
        "value": 25.00015154687274
      },
      {
        "time": "2025-10-23",
        "value": 25.024335393271357
      },
      {
        "time": "2025-10-24",
        "value": 25.073803344859954
      },
      {
        "time": "2025-10-27",
        "value": 25.104032108091975
      },
      {
        "time": "2025-10-28",
        "value": 25.10727090678871
      },
      {
        "time": "2025-10-29",
        "value": 25.175740810508493
      },
      {
        "time": "2025-10-30",
        "value": 25.281896714802798
      },
      {
        "time": "2025-10-31",
        "value": 25.374651484573803
      },
      {
        "time": "2025-11-03",
        "value": 25.432838558073183
      },
      {
        "time": "2025-11-04",
        "value": 25.29816270547833
      },
      {
        "time": "2025-11-05",
        "value": 25.246961303235345
      },
      {
        "time": "2025-11-06",
        "value": 25.12071909254196
      },
      {
        "time": "2025-11-07",
        "value": 25.29904282076867
      },
      {
        "time": "2025-11-10",
        "value": 24.92477117031434
      },
      {
        "time": "2025-11-11",
        "value": 24.492254909476248
      },
      {
        "time": "2025-11-12",
        "value": 24.27423615812196
      },
      {
        "time": "2025-11-13",
        "value": 23.99473937600084
      },
      {
        "time": "2025-11-14",
        "value": 23.652358969104313
      },
      {
        "time": "2025-11-17",
        "value": 22.946502980420092
      },
      {
        "time": "2025-11-18",
        "value": 22.362627052731995
      },
      {
        "time": "2025-11-19",
        "value": 21.804406931791306
      },
      {
        "time": "2025-11-20",
        "value": 21.38004209151725
      },
      {
        "time": "2025-11-21",
        "value": 21.23989618925306
      },
      {
        "time": "2025-11-24",
        "value": 21.206402501296523
      },
      {
        "time": "2025-11-25",
        "value": 21.226838307399035
      },
      {
        "time": "2025-11-26",
        "value": 21.22154290971075
      },
      {
        "time": "2025-11-28",
        "value": 21.28534204747867
      },
      {
        "time": "2025-12-01",
        "value": 21.426532470626757
      },
      {
        "time": "2025-12-02",
        "value": 21.550474649269944
      },
      {
        "time": "2025-12-03",
        "value": 21.577871264949167
      },
      {
        "time": "2025-12-04",
        "value": 21.654549042230595
      },
      {
        "time": "2025-12-05",
        "value": 21.67814085959091
      },
      {
        "time": "2025-12-08",
        "value": 21.75838953335228
      },
      {
        "time": "2025-12-09",
        "value": 21.7547641679726
      },
      {
        "time": "2025-12-10",
        "value": 21.742760463830336
      },
      {
        "time": "2025-12-11",
        "value": 21.720768961328776
      },
      {
        "time": "2025-12-12",
        "value": 21.720765398875464
      },
      {
        "time": "2025-12-15",
        "value": 21.728983495117724
      },
      {
        "time": "2025-12-16",
        "value": 21.953449172632457
      },
      {
        "time": "2025-12-17",
        "value": 22.240861011697422
      },
      {
        "time": "2025-12-18",
        "value": 22.535969132826903
      },
      {
        "time": "2025-12-19",
        "value": 22.789480075049187
      },
      {
        "time": "2025-12-22",
        "value": 22.687172535024416
      },
      {
        "time": "2025-12-23",
        "value": 22.485744326743852
      },
      {
        "time": "2025-12-24",
        "value": 22.356617797634428
      },
      {
        "time": "2025-12-26",
        "value": 22.289296953155468
      },
      {
        "time": "2025-12-29",
        "value": 22.081073563307427
      },
      {
        "time": "2025-12-30",
        "value": 21.926745291624826
      },
      {
        "time": "2025-12-31",
        "value": 21.648936542232995
      },
      {
        "time": "2026-01-02",
        "value": 21.37884081446998
      },
      {
        "time": "2026-01-05",
        "value": 21.102462495580195
      },
      {
        "time": "2026-01-06",
        "value": 20.98873727078205
      },
      {
        "time": "2026-01-07",
        "value": 20.630470604514503
      },
      {
        "time": "2026-01-08",
        "value": 20.422726774441898
      },
      {
        "time": "2026-01-09",
        "value": 20.29679756620576
      },
      {
        "time": "2026-01-12",
        "value": 20.214014741592585
      },
      {
        "time": "2026-01-13",
        "value": 20.087033278940567
      },
      {
        "time": "2026-01-14",
        "value": 19.927512624098963
      },
      {
        "time": "2026-01-15",
        "value": 19.859348215624372
      },
      {
        "time": "2026-01-16",
        "value": 19.757130611341964
      },
      {
        "time": "2026-01-20",
        "value": 19.459142688958398
      },
      {
        "time": "2026-01-21",
        "value": 19.14621320062502
      },
      {
        "time": "2026-01-22",
        "value": 18.952832771907545
      },
      {
        "time": "2026-01-23",
        "value": 18.706127206794502
      },
      {
        "time": "2026-01-26",
        "value": 18.543532334048752
      },
      {
        "time": "2026-01-27",
        "value": 18.438842104861195
      },
      {
        "time": "2026-01-28",
        "value": 18.26463199358343
      },
      {
        "time": "2026-01-29",
        "value": 18.238959191154674
      },
      {
        "time": "2026-01-30",
        "value": 18.19038554538825
      },
      {
        "time": "2026-02-02",
        "value": 18.21109831949591
      },
      {
        "time": "2026-02-03",
        "value": 18.09524221655669
      },
      {
        "time": "2026-02-04",
        "value": 18.203954507317757
      },
      {
        "time": "2026-02-05",
        "value": 18.126315944293847
      },
      {
        "time": "2026-02-06",
        "value": 18.168899364856426
      },
      {
        "time": "2026-02-09",
        "value": 18.2430915916707
      },
      {
        "time": "2026-02-10",
        "value": 18.339517380646534
      },
      {
        "time": "2026-02-11",
        "value": 18.45801612184495
      },
      {
        "time": "2026-02-12",
        "value": 18.447277134216183
      },
      {
        "time": "2026-02-13",
        "value": 18.516483274281413
      },
      {
        "time": "2026-02-17",
        "value": 18.40584739777956
      },
      {
        "time": "2026-02-18",
        "value": 18.221100113734323
      },
      {
        "time": "2026-02-19",
        "value": 18.061317070780657
      },
      {
        "time": "2026-02-20",
        "value": 17.9887174660325
      },
      {
        "time": "2026-02-23",
        "value": 17.868885797843834
      },
      {
        "time": "2026-02-24",
        "value": 17.73399439046207
      },
      {
        "time": "2026-02-25",
        "value": 17.618038491869246
      },
      {
        "time": "2026-02-26",
        "value": 17.60159714475861
      },
      {
        "time": "2026-02-27",
        "value": 17.593171363447325
      },
      {
        "time": "2026-03-02",
        "value": 17.56601573782793
      },
      {
        "time": "2026-03-03",
        "value": 17.591395447492154
      },
      {
        "time": "2026-03-04",
        "value": 17.595396011690756
      },
      {
        "time": "2026-03-05",
        "value": 17.63035147971008
      },
      {
        "time": "2026-03-06",
        "value": 17.62329603597113
      },
      {
        "time": "2026-03-09",
        "value": 17.63978908459475
      },
      {
        "time": "2026-03-10",
        "value": 17.637329046510885
      },
      {
        "time": "2026-03-11",
        "value": 17.686818220419493
      },
      {
        "time": "2026-03-12",
        "value": 17.74867369620948
      },
      {
        "time": "2026-03-13",
        "value": 17.743262757476213
      },
      {
        "time": "2026-03-16",
        "value": 17.751980744638683
      },
      {
        "time": "2026-03-17",
        "value": 17.78574381647291
      },
      {
        "time": "2026-03-18",
        "value": 17.81134921543725
      },
      {
        "time": "2026-03-19",
        "value": 17.86754862600581
      },
      {
        "time": "2026-03-20",
        "value": 17.864545361592572
      },
      {
        "time": "2026-03-23",
        "value": 17.92672259583179
      },
      {
        "time": "2026-03-24",
        "value": 18.040159136585952
      },
      {
        "time": "2026-03-25",
        "value": 18.105089623338316
      },
      {
        "time": "2026-03-26",
        "value": 18.096350559362172
      },
      {
        "time": "2026-03-27",
        "value": 18.067919430782013
      },
      {
        "time": "2026-03-30",
        "value": 18.113805791321013
      },
      {
        "time": "2026-03-31",
        "value": 18.120532534784882
      },
      {
        "time": "2026-04-01",
        "value": 18.12287649710581
      },
      {
        "time": "2026-04-02",
        "value": 18.09379141423606
      },
      {
        "time": "2026-04-06",
        "value": 18.093199858496423
      },
      {
        "time": "2026-04-07",
        "value": 18.09120397062999
      },
      {
        "time": "2026-04-08",
        "value": 18.129923043926894
      },
      {
        "time": "2026-04-09",
        "value": 18.11624113077752
      },
      {
        "time": "2026-04-10",
        "value": 18.037319038308596
      },
      {
        "time": "2026-04-13",
        "value": 18.03498248109299
      },
      {
        "time": "2026-04-14",
        "value": 18.052473210705553
      },
      {
        "time": "2026-04-15",
        "value": 18.063756969430244
      },
      {
        "time": "2026-04-16",
        "value": 18.12458806480355
      },
      {
        "time": "2026-04-17",
        "value": 18.137742564660364
      },
      {
        "time": "2026-04-20",
        "value": 18.24608640416382
      },
      {
        "time": "2026-04-21",
        "value": 18.05156599850437
      },
      {
        "time": "2026-04-22",
        "value": 18.02971110895105
      },
      {
        "time": "2026-04-23",
        "value": 18.014345579284715
      },
      {
        "time": "2026-04-24",
        "value": 18.02379320599468
      },
      {
        "time": "2026-04-27",
        "value": 18.02911500923365
      },
      {
        "time": "2026-04-28",
        "value": 18.064119966356095
      }
    ],
    "supportLine": 18.07
  }
}